llm_toolchain/__init__.py
llm_toolchain/adapters/__init__.py
llm_toolchain/adapters/base.py
llm_toolchain/adapters/genai.py
llm_toolchain/adapters/openai.py
llm_toolchain/adapters/prompt.py
llm_toolchain/adapters/vertexai.py
llm_toolchain/core.py
llm_toolchain/integrations/langchain.py
llm_toolchain/models.py
llm_toolchain/selectors/base.py
llm_toolchain/selectors/semantic.py
llm_toolchain/tools/__init__.py
llm_toolchain/tools/calendar_creator.py
llm_toolchain/tools/chess.py
llm_toolchain/tools/file_system.py
llm_toolchain/tools/finance.py
llm_toolchain/tools/geolocation.py
llm_toolchain/tools/graph_visualizer.py
llm_toolchain/tools/python_tool.py
llm_toolchain/tools/regex_tester.py
llm_toolchain/tools/unit_conversion.py
llm_toolchain/tools/weather.py
llm_toolchain/tools/web_browser.py
llm_toolchain/utils/formatting.py
llm_toolchain/utils/schema_generator.py
llm_toolchain-0.2.5.dist-info/LICENSE
llm_toolchain-0.2.5.dist-info/METADATA
llm_toolchain-0.2.5.dist-info/WHEEL
llm_toolchain-0.2.5.dist-info/RECORD
