Metadata-Version: 2.3
Name: llm_toolchain
Version: 0.2.5
Summary: Giving LLMs the tools for real impact.
Author: Kilian Schulz
Author-email: kilianschulz@kilianschulz.com
Requires-Python: >=3.11,<4.0
Classifier: Programming Language :: Python :: 3
Classifier: Programming Language :: Python :: 3.11
Classifier: Programming Language :: Python :: 3.12
Classifier: Programming Language :: Python :: 3.13
Provides-Extra: gemini
